oakestra_utils/__init__.py
oakestra_utils/types/__init__.py
oakestra_utils/types/common.py
oakestra_utils/types/statuses.py
oakestra_utils-0.2.0.dist-info/METADATA
oakestra_utils-0.2.0.dist-info/WHEEL
oakestra_utils-0.2.0.dist-info/RECORD
