Metadata-Version: 2.1
Name: oakestra_utils
Version: 0.2.0
Summary: A library containing common utilities for Oakestra
Author: Alexander Malyuk
Author-email: malyuk.alexander1999@gmail.com
Requires-Python: >=3.10,<4.0
Classifier: Programming Language :: Python :: 3
Classifier: Programming Language :: Python :: 3.10
Classifier: Programming Language :: Python :: 3.11
Classifier: Programming Language :: Python :: 3.12
